ghpythonremote/__init__.py
ghpythonremote/_configure_ironpython_installation.py
ghpythonremote/connectors.py
ghpythonremote/ghcompservice.py
ghpythonremote/ghuserobjects.py
ghpythonremote/helpers.py
ghpythonremote/monkey.py
ghpythonremote/pythonservice.py
ghpythonremote/version.py
ghpythonremote/examples/CPython_to_GH.py
ghpythonremote/examples/GH_python_remote.ghx
ghpythonremote/examples/GH_python_remote_plt_example.ghx
ghpythonremote/examples/TestClusterGHPythonRemote.ghuser
ghpythonremote/examples/curves.3dm
ghpythonremote/ghcluster/GHPythonRemote.ghuser
gh_python_remote-1.4.6.dist-info/LICENSE.txt
gh_python_remote-1.4.6.dist-info/METADATA
gh_python_remote-1.4.6.dist-info/WHEEL
gh_python_remote-1.4.6.dist-info/top_level.txt
gh_python_remote-1.4.6.dist-info/RECORD
