Metadata-Version: 2.1
Name: gh-python-remote
Version: 1.4.6
Summary: GH Python Remote is a package to get Rhinoceros3D/Grasshopper and Python to collaborate better: connect an external python instance to Grasshopper, and vice-versa.
Home-page: https://github.com/Digital-Structures/ghpythonremote
Author: Pierre Cuvilliers
Author-email: pcuvil@mit.edu
License: MIT
Keywords: CAD design engineering scientific numpy scipy IronPython Rhinoceros3D
Platform: Windows
Classifier: Development Status :: 5 - Production/Stable
Classifier: Intended Audience :: Developers
Classifier: Intended Audience :: End Users/Desktop
Classifier: Topic :: Software Development :: Interpreters
Classifier: Topic :: Scientific/Engineering
Classifier: License :: OSI Approved :: MIT License
Classifier: Programming Language :: Python :: 2 :: Only
Classifier: Programming Language :: Python :: 2.7
Classifier: Programming Language :: Python :: Implementation :: CPython
Classifier: Programming Language :: Python :: Implementation :: IronPython
Requires-Python: >=2.6,<3
Requires-Dist: plumbum (==1.7.2)
Requires-Dist: rpyc (==4.1.5)
Provides-Extra: dev
Requires-Dist: check-manifest ; extra == 'dev'
Provides-Extra: test
Requires-Dist: coverage ; extra == 'test'
